misago_pypi_plugin/__init__.py
misago_pypi_plugin/misago_plugin.py
misago_pypi_plugin-0.2.dist-info/METADATA
misago_pypi_plugin-0.2.dist-info/WHEEL
misago_pypi_plugin-0.2.dist-info/licenses/LICENSE
misago_pypi_plugin-0.2.dist-info/RECORD
