Metadata-Version: 2.1
Name: misago-pypi-plugin
Version: 0.2
Summary: Minimal Misago plugin for testing support for installing plugins from PyPI.
Author-email: Rafał Pitoń <kontakt@rpiton.com>
License: BSD 3-Clause License
License-File: LICENSE
Classifier: Development Status :: 4 - Beta
Classifier: Intended Audience :: Developers
Classifier: License :: OSI Approved :: GNU General Public License v2 (GPLv2)
Classifier: Operating System :: OS Independent
Classifier: Programming Language :: Python
Classifier: Programming Language :: Python :: 3.12
Classifier: Topic :: Software Development :: Libraries :: Python Modules
